newcalls/__init__.py
newcalls/__version__.py
newcalls/binding.py
newcalls/environment.py
newcalls/exceptions.py
newcalls/ffprobe.py
newcalls/file_manager.py
newcalls/newcalls.py
newcalls/newcalls_session.py
newcalls/scaffold.py
newcalls/stream_type.py
newcalls/sync.py
newcalls/version_manager.py
newcalls/custom_api/__init__.py
newcalls/custom_api/custom_api.py
newcalls/dist/binding.js
newcalls/dist/buffer_optimized.js
newcalls/dist/ffmpeg_reader.js
newcalls/dist/file_reader.js
newcalls/dist/index.js
newcalls/dist/rtc-connection.js
newcalls/dist/sdp-builder.js
newcalls/dist/stream.js
newcalls/dist/tgcalls.js
newcalls/dist/types.js
newcalls/dist/utils.js
newcalls/handlers/__init__.py
newcalls/handlers/handlers_holder.py
newcalls/media_devices/__init__.py
newcalls/media_devices/device_info.py
newcalls/media_devices/media_devices.py
newcalls/media_devices/screen_info.py
newcalls/methods/__init__.py
newcalls/methods/core/__init__.py
newcalls/methods/core/binding_runner.py
newcalls/methods/core/join_voice_call.py
newcalls/methods/core/leave_voice_call.py
newcalls/methods/core/set_video_call_status.py
newcalls/methods/decorators/__init__.py
newcalls/methods/decorators/on_closed_voice_chat.py
newcalls/methods/decorators/on_group_call_invite.py
newcalls/methods/decorators/on_kicked.py
newcalls/methods/decorators/on_left.py
newcalls/methods/decorators/on_participants_change.py
newcalls/methods/decorators/on_raw_update.py
newcalls/methods/decorators/on_stream_end.py
newcalls/methods/groups/__init__.py
newcalls/methods/groups/active_calls.py
newcalls/methods/groups/calls.py
newcalls/methods/groups/change_volume_call.py
newcalls/methods/groups/get_active_call.py
newcalls/methods/groups/get_call.py
newcalls/methods/groups/get_participants.py
newcalls/methods/groups/join_group_call.py
newcalls/methods/groups/leave_group_call.py
newcalls/methods/handlers/__init__.py
newcalls/methods/handlers/raw_update_handler.py
newcalls/methods/handlers/stream_ended_handler.py
py_newcalls-0.0.1.dist-info/LICENSE
py_newcalls-0.0.1.dist-info/METADATA
py_newcalls-0.0.1.dist-info/WHEEL
py_newcalls-0.0.1.dist-info/top_level.txt
py_newcalls-0.0.1.dist-info/RECORD
